celitech/__init__.py
celitech/sdk.py
celitech/sdk_async.py
celitech/hooks/__init__.py
celitech/hooks/hook.py
celitech/models/__init__.py
celitech/models/bad_request.py
celitech/models/create_purchase_ok_response.py
celitech/models/create_purchase_request.py
celitech/models/create_purchase_v2_ok_response.py
celitech/models/create_purchase_v2_request.py
celitech/models/edit_purchase_ok_response.py
celitech/models/edit_purchase_request.py
celitech/models/get_access_token_ok_response.py
celitech/models/get_access_token_request.py
celitech/models/get_esim_device_ok_response.py
celitech/models/get_esim_history_ok_response.py
celitech/models/get_esim_ok_response.py
celitech/models/get_purchase_consumption_ok_response.py
celitech/models/list_destinations_ok_response.py
celitech/models/list_packages_ok_response.py
celitech/models/list_purchases_ok_response.py
celitech/models/token_ok_response.py
celitech/models/top_up_esim_ok_response.py
celitech/models/top_up_esim_request.py
celitech/models/unauthorized.py
celitech/models/utils/__init__.py
celitech/models/utils/base_model.py
celitech/models/utils/cast_models.py
celitech/models/utils/json_map.py
celitech/models/utils/one_of_base_model.py
celitech/models/utils/sentinel.py
celitech/net/__init__.py
celitech/net/environment/__init__.py
celitech/net/environment/environment.py
celitech/net/headers/__init__.py
celitech/net/headers/base_header.py
celitech/net/oauth/token_manager.py
celitech/net/request_chain/__init__.py
celitech/net/request_chain/request_chain.py
celitech/net/request_chain/handlers/__init__.py
celitech/net/request_chain/handlers/base_handler.py
celitech/net/request_chain/handlers/hook_handler.py
celitech/net/request_chain/handlers/http_handler.py
celitech/net/request_chain/handlers/oauth_handler.py
celitech/net/request_chain/handlers/retry_handler.py
celitech/net/transport/__init__.py
celitech/net/transport/api_error.py
celitech/net/transport/request.py
celitech/net/transport/request_error.py
celitech_sdk-1.3.60.dist-info/licenses/LICENSE
celitech_sdk-1.3.60.dist-info/METADATA
celitech_sdk-1.3.60.dist-info/WHEEL
celitech_sdk-1.3.60.dist-info/top_level.txt
celitech_sdk-1.3.60.dist-info/RECORD
