Metadata-Version: 2.4
Name: celitech-sdk
Version: 1.3.60
Summary: Welcome to the CELITECH API documentation!
License: MIT
Requires-Python: >=3.9
License-File: LICENSE
Requires-Dist: requests>=2.31.0
Dynamic: license-file
